StockerDataframe/__init__.py
StockerDataframe/gainers.py
StockerDataframe/historicaldata.py
StockerDataframe/losers.py
StockerDataframe-1.2.1.dist-info/LICENSE
StockerDataframe-1.2.1.dist-info/METADATA
StockerDataframe-1.2.1.dist-info/WHEEL
StockerDataframe-1.2.1.dist-info/top_level.txt
StockerDataframe-1.2.1.dist-info/RECORD
