Metadata-Version: 2.1
Name: StockerDataframe
Version: 1.2.1
Summary: A unique tool for better analysis of Stock Market
Home-page: https://github.com/Bhard27/StockerDataframe
Author: Pranjal
Author-email: pranjal27bhardwaj@gmail.com
License: GPL-3.0 License
Platform: UNKNOWN
